irtorch/__init__.py
irtorch/_internal_utils.py
irtorch/activation_functions.py
irtorch/bit_scales.py
irtorch/config.py
irtorch/cross_validation.py
irtorch/evaluation.py
irtorch/evaluator.py
irtorch/gaussian_mixture_model.py
irtorch/irt_dataset.py
irtorch/latent_variable_functions.py
irtorch/load_dataset.py
irtorch/outlier_detector.py
irtorch/plotter.py
irtorch/plotting.py
irtorch/quantile_mv_normal.py
irtorch/timer.py
irtorch/torch_modules.py
irtorch/utils.py
irtorch/datasets/big_five/big_five.pt
irtorch/datasets/big_five/codebook.txt
irtorch/datasets/big_five/items.txt
irtorch/datasets/national_mathematics/mathematics_1.pt
irtorch/datasets/national_mathematics/mathematics_2.pt
irtorch/datasets/swedish_sat/swesat22b_nominal_quant.pt
irtorch/datasets/swedish_sat/swesat22b_nominal_verb.pt
irtorch/datasets/swedish_sat/swesat22b_quant.pt
irtorch/datasets/swedish_sat/swesat22b_quant_correct.txt
irtorch/datasets/swedish_sat/swesat22b_verb.pt
irtorch/datasets/swedish_sat/swesat22b_verb_correct.txt
irtorch/estimation_algorithms/__init__.py
irtorch/estimation_algorithms/ae.py
irtorch/estimation_algorithms/base_irt_algorithm.py
irtorch/estimation_algorithms/jml.py
irtorch/estimation_algorithms/mml.py
irtorch/estimation_algorithms/vae.py
irtorch/estimation_algorithms/encoders/__init__.py
irtorch/estimation_algorithms/encoders/base_encoder.py
irtorch/estimation_algorithms/encoders/bounded_encoder.py
irtorch/estimation_algorithms/encoders/standard_encoder.py
irtorch/estimation_algorithms/encoders/variational_encoder.py
irtorch/models/__init__.py
irtorch/models/base_irt_model.py
irtorch/models/generalized_partial_credit.py
irtorch/models/graded_response.py
irtorch/models/model_mix.py
irtorch/models/monotone_b_spline.py
irtorch/models/monotone_nn.py
irtorch/models/monotone_polynomial.py
irtorch/models/nested_logit.py
irtorch/models/nominal_response.py
irtorch/models/one_parameter_logistic.py
irtorch/models/surprisal.py
irtorch/models/surprisal_spline.py
irtorch-0.5.2.dist-info/LICENSE.txt
irtorch-0.5.2.dist-info/METADATA
irtorch-0.5.2.dist-info/WHEEL
irtorch-0.5.2.dist-info/top_level.txt
irtorch-0.5.2.dist-info/RECORD
