Metadata-Version: 2.1
Name: irtorch
Version: 0.5.2
Summary: IRTorch: An item response theory package for python.
Home-page: https://github.com/joakimwallmark/irtorch
Author: Joakim Wallmark
Author-email: wallmark.joakim@gmail.com
License: MIT
Requires-Python: >=3.10
License-File: LICENSE.txt
Requires-Dist: torch <4.0.0,>=2.1.1
Requires-Dist: numpy <3.0.0,>=1.24.1
Requires-Dist: pandas <4.0.0,>=2.2.0
Requires-Dist: plotly <7.0.0,>=5.19.0
Requires-Dist: factor-analyzer >=0.4.1
Requires-Dist: splinetorch >=0.0.2
